<?xml version='1.0' encoding='UTF-8' standalone='yes' ?><hierarchy rotation="0"><node index="0" text="" resource-id="" class="android.widget.FrameLayout" package="com.fitnova.app" content-desc="" checkable="false" checked="false" clickable="false" enabled="true" focusable="false" focused="false" scrollable="false" long-clickable="false" password="false" selected="false" bounds="[0,0][1344,2992]" drawing-order="0" hint=""><node index="0" text="" resource-id="" class="android.widget.LinearLayout" package="com.fitnova.app" content-desc="" checkable="false" checked="false" clickable="false" enabled="true" focusable="false" focused="false" scrollable="false" long-clickable="false" password="false" selected="false" bounds="[0,0][1344,2992]" drawing-order="1" hint=""><node index="0" text="" resource-id="android:id/content" class="android.widget.FrameLayout" package="com.fitnova.app" content-desc="" checkable="false" checked="false" clickable="false" enabled="true" focusable="false" focused="false" scrollable="false" long-clickable="false" password="false" selected="false" bounds="[0,0][1344,2992]" drawing-order="2" hint=""><node index="0" text="" resource-id="" class="android.widget.FrameLayout" package="com.fitnova.app" content-desc="" checkable="false" checked="false" clickable="false" enabled="true" focusable="true" focused="false" scrollable="false" long-clickable="false" password="false" selected="false" bounds="[0,0][1344,2992]" drawing-order="1" hint=""><node index="0" text="" resource-id="" class="android.view.View" package="com.fitnova.app" content-desc="" checkable="false" checked="false" clickable="false" enabled="true" focusable="false" focused="false" scrollable="false" long-clickable="false" password="false" selected="false" bounds="[0,0][1344,2992]" drawing-order="0" hint=""><node index="0" text="" resource-id="" class="android.view.View" package="com.fitnova.app" content-desc="" checkable="false" checked="false" clickable="false" enabled="true" focusable="false" focused="false" scrollable="false" long-clickable="false" password="false" selected="false" bounds="[0,0][1344,2992]" drawing-order="0" hint=""><node index="0" text="" resource-id="" class="android.view.View" package="com.fitnova.app" content-desc="" checkable="false" checked="false" clickable="false" enabled="true" focusable="false" focused="false" scrollable="false" long-clickable="false" password="false" selected="false" bounds="[0,0][1344,2992]" drawing-order="0" hint=""><node index="0" text="" resource-id="" class="android.view.View" package="com.fitnova.app" content-desc="" checkable="false" checked="false" clickable="false" enabled="true" focusable="false" focused="false" scrollable="false" long-clickable="false" password="false" selected="false" bounds="[0,0][1344,2992]" drawing-order="0" hint=""><node index="0" text="" resource-id="" class="android.view.View" package="com.fitnova.app" content-desc="" checkable="false" checked="false" clickable="false" enabled="true" focusable="false" focused="false" scrollable="false" long-clickable="false" password="false" selected="false" bounds="[0,0][1344,2992]" drawing-order="0" hint=""><node index="0" text="" resource-id="" class="android.view.View" package="com.fitnova.app" content-desc="" checkable="false" checked="false" clickable="false" enabled="true" focusable="false" focused="false" scrollable="false" long-clickable="false" password="false" selected="false" bounds="[0,136][1344,2920]" drawing-order="0" hint=""><node index="0" text="" resource-id="" class="android.view.View" package="com.fitnova.app" content-desc="" checkable="false" checked="false" clickable="false" enabled="true" focusable="false" focused="false" scrollable="false" long-clickable="false" password="false" selected="false" bounds="[252,1000][1092,2056]" drawing-order="0" hint=""><node index="0" text="" resource-id="" class="android.view.View" package="com.fitnova.app" content-desc="New alarm" checkable="false" checked="false" clickable="false" enabled="true" focusable="true" focused="false" scrollable="false" long-clickable="false" password="false" selected="false" bounds="[324,1072][1020,1168]" drawing-order="0" hint="" /><node index="1" text="" resource-id="" class="android.view.View" package="com.fitnova.app" content-desc="" checkable="false" checked="false" clickable="false" enabled="true" focusable="false" focused="false" scrollable="false" long-clickable="false" password="false" selected="false" bounds="[324,1216][1020,1768]" drawing-order="0" hint=""><node NAF="true" index="0" text="" resource-id="" class="android.widget.EditText" package="com.fitnova.app" content-desc="" checkable="false" checked="false" clickable="true" enabled="true" focusable="true" focused="false" scrollable="false" long-clickable="false" password="false" selected="false" bounds="[324,1216][1020,1384]" drawing-order="0" hint="Label" /><node index="1" text="" resource-id="" class="android.widget.Button" package="com.fitnova.app" content-desc="Repeat&#10;Daily" checkable="false" checked="false" clickable="true" enabled="true" focusable="true" focused="false" scrollable="false" long-clickable="false" password="false" selected="false" bounds="[324,1420][1020,1588]" drawing-order="0" hint="" /><node index="2" text="" resource-id="" class="android.view.View" package="com.fitnova.app" content-desc="Time: 6:00 AM" checkable="false" checked="false" clickable="false" enabled="true" focusable="true" focused="false" scrollable="false" long-clickable="false" password="false" selected="false" bounds="[324,1666][762,1726]" drawing-order="0" hint="" /><node index="3" text="" resource-id="" class="android.widget.Button" package="com.fitnova.app" content-desc="Pick time" checkable="false" checked="false" clickable="true" enabled="true" focusable="true" focused="false" scrollable="false" long-clickable="false" password="false" selected="false" bounds="[762,1624][1020,1768]" drawing-order="0" hint="" /></node><node index="2" text="" resource-id="" class="android.widget.Button" package="com.fitnova.app" content-desc="Cancel" checkable="false" checked="false" clickable="true" enabled="true" focusable="true" focused="false" scrollable="false" long-clickable="false" password="false" selected="false" bounds="[496,1840][712,1984]" drawing-order="0" hint="" /><node index="3" text="" resource-id="" class="android.widget.Button" package="com.fitnova.app" content-desc="Create" checkable="false" checked="false" clickable="true" enabled="true" focusable="true" focused="false" scrollable="false" long-clickable="false" password="false" selected="false" bounds="[736,1840][1020,1984]" drawing-order="0" hint="" /></node></node></node></node></node><node index="1" text="" resource-id="" class="android.view.View" package="com.fitnova.app" content-desc="Dismiss" checkable="false" checked="false" clickable="true" enabled="true" focusable="true" focused="false" scrollable="false" long-clickable="false" password="false" selected="false" bounds="[0,0][1344,2992]" drawing-order="0" hint="" /></node></node></node></node></node></node></hierarchy>